brs_utils/__init__.py
brs_utils/file.py
brs_utils/list.py
brs_utils/misc.py
brs_utils/print.py
brs_utils-0.2.6.dist-info/LICENSE
brs_utils-0.2.6.dist-info/METADATA
brs_utils-0.2.6.dist-info/WHEEL
brs_utils-0.2.6.dist-info/top_level.txt
brs_utils-0.2.6.dist-info/RECORD
