Metadata-Version: 2.1
Name: brs-utils
Version: 0.2.6
Summary: BRSynth Utilities
Home-page: https://github.com/brsynth/brs-utils
Author: Melchior du Lac, Joan Hérisson
Author-email: joan.herisson@univ-evry.fr
License: MIT
Platform: UNKNOWN
Classifier: Programming Language :: Python :: 3
Classifier: License :: OSI Approved :: MIT License
Classifier: Operating System :: OS Independent
Requires-Python: >=3.5
Requires-Dist: requests
